ares_datamodel/__init__.py
ares_datamodel/analysis_overview_pb2.py
ares_datamodel/analysis_overview_pb2.pyi
ares_datamodel/analysis_overview_pb2_grpc.py
ares_datamodel/ares_analysis_service_pb2.py
ares_datamodel/ares_analysis_service_pb2.pyi
ares_datamodel/ares_analysis_service_pb2_grpc.py
ares_datamodel/ares_analyzer_management_service_pb2.py
ares_datamodel/ares_analyzer_management_service_pb2.pyi
ares_datamodel/ares_analyzer_management_service_pb2_grpc.py
ares_datamodel/ares_automation_pb2.py
ares_datamodel/ares_automation_pb2.pyi
ares_datamodel/ares_automation_pb2_grpc.py
ares_datamodel/ares_campaign_tag_pb2.py
ares_datamodel/ares_campaign_tag_pb2.pyi
ares_datamodel/ares_campaign_tag_pb2_grpc.py
ares_datamodel/ares_data_schema_pb2.py
ares_datamodel/ares_data_schema_pb2.pyi
ares_datamodel/ares_data_schema_pb2_grpc.py
ares_datamodel/ares_data_type_pb2.py
ares_datamodel/ares_data_type_pb2.pyi
ares_datamodel/ares_data_type_pb2_grpc.py
ares_datamodel/ares_devices_pb2.py
ares_datamodel/ares_devices_pb2.pyi
ares_datamodel/ares_devices_pb2_grpc.py
ares_datamodel/ares_event_pb2.py
ares_datamodel/ares_event_pb2.pyi
ares_datamodel/ares_event_pb2_grpc.py
ares_datamodel/ares_notification_pb2.py
ares_datamodel/ares_notification_pb2.pyi
ares_datamodel/ares_notification_pb2_grpc.py
ares_datamodel/ares_outcome_enum_pb2.py
ares_datamodel/ares_outcome_enum_pb2.pyi
ares_datamodel/ares_outcome_enum_pb2_grpc.py
ares_datamodel/ares_planner_management_service_pb2.py
ares_datamodel/ares_planner_management_service_pb2.pyi
ares_datamodel/ares_planner_management_service_pb2_grpc.py
ares_datamodel/ares_safety_service_pb2.py
ares_datamodel/ares_safety_service_pb2.pyi
ares_datamodel/ares_safety_service_pb2_grpc.py
ares_datamodel/ares_scripting_service_pb2.py
ares_datamodel/ares_scripting_service_pb2.pyi
ares_datamodel/ares_scripting_service_pb2_grpc.py
ares_datamodel/ares_server_info_pb2.py
ares_datamodel/ares_server_info_pb2.pyi
ares_datamodel/ares_server_info_pb2_grpc.py
ares_datamodel-0.16.0.dist-info/METADATA
ares_datamodel-0.16.0.dist-info/WHEEL
ares_datamodel-0.16.0.dist-info/RECORD
