Metadata-Version: 2.4
Name: ares_datamodel
Version: 0.16.0
Summary: Datamodel/messaging for ARES communications
Project-URL: Homepage, https://github.com/AFRL-ARES/ARES-datamodel
Project-URL: Issues, https://github.com/AFRL-ARES/ARES-datamodel/issues
Author-email: DCS <ababeckis@dcscorp.com>
License: MIT License
Classifier: Operating System :: OS Independent
Classifier: Programming Language :: Python :: 3
Requires-Python: >=3.9
